swag_client/__about__.py
swag_client/__init__.py
swag_client/backend.py
swag_client/cli.py
swag_client/compat.py
swag_client/exceptions.py
swag_client/swag.py
swag_client/util.py
swag_client/backends/__init__.py
swag_client/backends/dynamodb.py
swag_client/backends/file.py
swag_client/backends/s3.py
swag_client/migrations/__init__.py
swag_client/migrations/migrations.py
swag_client/migrations/versions/__init__.py
swag_client/migrations/versions/v2.py
swag_client/schemas/__init__.py
swag_client/schemas/v1.py
swag_client/schemas/v2.py
swag_client/schemas/validators.py
swag_client/schemas/services/__init__.py
swag_client/tests/__init__.py
swag_client/tests/conftest.py
swag_client/tests/test_swag.py
swag_client-3.0.0.dist-info/LICENSE
swag_client-3.0.0.dist-info/METADATA
swag_client-3.0.0.dist-info/WHEEL
swag_client-3.0.0.dist-info/entry_points.txt
swag_client-3.0.0.dist-info/top_level.txt
swag_client-3.0.0.dist-info/RECORD
