Metadata-Version: 2.1
Name: swag-client
Version: 3.0.0
Summary: Cloud multi-account metadata management tool.
Home-page: https://github.com/Netflix-Skunkworks/swag-client
Author: The swag developers
Author-email: oss@netflix.com
License: UNKNOWN
Keywords: aws,account_management
Platform: UNKNOWN
Requires-Dist: marshmallow (>=3.5.0)
Requires-Dist: boto3 (>=1.3.7)
Requires-Dist: tabulate (>=0.7.7)
Requires-Dist: dogpile.cache (>=0.6.4)
Requires-Dist: click (>=6.7)
Requires-Dist: click-log (>=0.2.1)
Requires-Dist: jmespath (>=0.9.3)
Requires-Dist: deepdiff (>=3.3.0)
Requires-Dist: retrying (>=1.3.3)
Requires-Dist: simplejson (>=3.16.0)
Provides-Extra: tests
Requires-Dist: pytest (==3.1.3) ; extra == 'tests'
Requires-Dist: moto ; extra == 'tests'
Requires-Dist: coveralls (==1.1) ; extra == 'tests'
